pusht/__init__.py
pusht/pusht_env.py
pusht/pusht_image_env.py
pusht/pymunk_override.py
sim_pusht-0.1.0.dist-info/METADATA
sim_pusht-0.1.0.dist-info/WHEEL
sim_pusht-0.1.0.dist-info/RECORD
